{
  "settings": {},
  "dependencies": [
    "MI Electronic Circuit"
  ],
  "tasks": {
    "16E814CBBEE5F8AB": {
      "type": "heracles:item",
      "item": "modern_industrialization:mv_steam_turbine"
    }
  },
  "rewards": {
    "0779AB058E70BD8E": {
      "type": "heracles:item",
      "item": {
        "id": "lootbags:loot_bag",
        "count": 1,
        "nbt": {
          "Color": 16425539,
          "Loot": "aof:loot_bags/mi/rare",
          "Name": "Modern Industrialization Rare Lootbag",
          "Type": "RARE"
        }
      }
    }
  },
  "display": {
    "title": "Acquire: modern_industrialization:mv_steam_turbine",
    "description": [
      "<task task=\"16E814CBBEE5F8AB\" quest=\"MI MV Steam Turbine\"/>",
      "<hr/>",
      "<hr/>",
      "<reward reward=\"0779AB058E70BD8E\" quest=\"MI MV Steam Turbine\"/>"
    ],
    "icon": {
      "type": "heracles:item",
      "item": "modern_industrialization:mv_steam_turbine"
    },
    "icon_background": "heracles:textures/gui/quest_backgrounds/rsquares.png",
    "groups": {
      "Modern Industrialization": {
        "position": [
          240,
          -96
        ]
      }
    }
  }
}