{
  "dependencies": [
    "fluid_transportation"
  ],
  "tasks": {},
  "rewards": {},
  "display": {
    "subtitle": {
      "text": ""
    },
    "description": [
      "# What's a tick?",
      "<br/>",
      "Calm down, calm down! A tick is the shortest amount of time that can be recorded. It's about a 20th of a second. The world runs off these \"ticks\" and you can use them to your advantage."
    ],
    "groups": {
      "Modern Industrialization": {
        "position": [
          100,
          50
        ]
      }
    },
    "icon": {
      "item": "supplementaries:clock_block",
      "type": "heracles:item"
    },
    "icon_background": "heracles:textures/gui/quest_backgrounds/default.png",
    "title": {
      "translate": "What's a tick?"
    }
  },
  "settings": {
    "individual_progress": false,
    "hidden": false,
    "unlockNotification": false
  }
}
